{"Entry":["Hero","StandardPage","NewRoute","Route","Link","Section","BodyCopy","Experiment","Feature","Grid","Header","Footer","Group","Person","Testimonial","ImageWithAiTags","PageMeta","SearchSection","Template","SearchInput","TestHero","DwExample","TestContainer","UiExtensionExample"],"SectionContentItem":["BodyCopy","Experiment","Feature","Footer","Grid","Header","Hero","Link","Person","Section","Testimonial"],"HeaderContentItem":["Grid","Link"],"FooterContentItem":["Grid","Link"],"GridContentItem":["Feature","Group","Link","Person","Testimonial"],"StandardPageContentItem":["Experiment","Hero","SearchSection","Section"]}